CHANGELOG.md
MANIFEST.in
README.md
setup.cfg
setup.py
versioneer.py
src/libreflow/__init__.py
src/libreflow.extensions.2h14.comp.egg-info/PKG-INFO
src/libreflow.extensions.2h14.comp.egg-info/SOURCES.txt
src/libreflow.extensions.2h14.comp.egg-info/dependency_links.txt
src/libreflow.extensions.2h14.comp.egg-info/requires.txt
src/libreflow.extensions.2h14.comp.egg-info/top_level.txt
src/libreflow/extensions/__init__.py
src/libreflow/extensions/2h14/__init__.py
src/libreflow/extensions/2h14/comp/__init__.py
src/libreflow/extensions/2h14/comp/_version.py
src/libreflow/extensions/2h14/comp/scripts/__init__.py
src/libreflow/extensions/2h14/comp/scripts/init_comp_scene.jsx
src/libreflow/extensions/2h14/comp/scripts/json2.js